cursers/__init__.py
cursers/app.py
cursers/thread.py
cursers-0.1.0.dist-info/METADATA
cursers-0.1.0.dist-info/WHEEL
cursers-0.1.0.dist-info/licenses/LICENSE
cursers-0.1.0.dist-info/RECORD
