Metadata-Version: 2.4
Name: cursers
Version: 0.1.0
Summary: A minimal threaded wrapper for Python curses 
Project-URL: repository, https://github.com/threeal/cursers.git
Project-URL: issues, https://github.com/threeal/cursers/issues
Author-email: Alfi Maulana <alfi.maulana.f@gmail.com>
License-Expression: MIT
License-File: LICENSE
Keywords: curses,terminal,threading,tui,wrapper
Classifier: Development Status :: 1 - Planning
Classifier: Environment :: Console
Classifier: Environment :: Console :: Curses
Classifier: Intended Audience :: Developers
Classifier: License :: OSI Approved :: MIT License
Classifier: Programming Language :: Python :: 3 :: Only
Classifier: Programming Language :: Python :: 3.13
Classifier: Topic :: Software Development :: Libraries :: Python Modules
Classifier: Topic :: Terminals
Requires-Python: >=3.13
